openbb/.build.lock
openbb/__init__.py
openbb/assets/reference.json
openbb/package/__init__.py
openbb/py.typed
openbb_core/__init__.py
openbb_core/api/app_loader.py
openbb_core/api/auth/user.py
openbb_core/api/dependency/__init__.py
openbb_core/api/dependency/coverage.py
openbb_core/api/dependency/system.py
openbb_core/api/exception_handlers.py
openbb_core/api/rest_api.py
openbb_core/api/router/__init__.py
openbb_core/api/router/commands.py
openbb_core/api/router/coverage.py
openbb_core/api/router/helpers/__init__.py
openbb_core/api/router/helpers/coverage_helpers.py
openbb_core/api/router/system.py
openbb_core/api/router/user.py
openbb_core/app/__init__.py
openbb_core/app/command_runner.py
openbb_core/app/constants.py
openbb_core/app/deprecation.py
openbb_core/app/extension_loader.py
openbb_core/app/logs/formatters/formatter_with_exceptions.py
openbb_core/app/logs/handlers/path_tracking_file_handler.py
openbb_core/app/logs/handlers_manager.py
openbb_core/app/logs/logging_service.py
openbb_core/app/logs/models/logging_settings.py
openbb_core/app/logs/utils/expired_files.py
openbb_core/app/logs/utils/utils.py
openbb_core/app/model/__init__.py
openbb_core/app/model/abstract/__init__.py
openbb_core/app/model/abstract/error.py
openbb_core/app/model/abstract/results.py
openbb_core/app/model/abstract/singleton.py
openbb_core/app/model/abstract/tagged.py
openbb_core/app/model/abstract/warning.py
openbb_core/app/model/api_settings.py
openbb_core/app/model/charts/chart.py
openbb_core/app/model/charts/charting_settings.py
openbb_core/app/model/command_context.py
openbb_core/app/model/credentials.py
openbb_core/app/model/defaults.py
openbb_core/app/model/example.py
openbb_core/app/model/extension.py
openbb_core/app/model/field.py
openbb_core/app/model/metadata.py
openbb_core/app/model/obbject.py
openbb_core/app/model/preferences.py
openbb_core/app/model/python_settings.py
openbb_core/app/model/results/__init__.py
openbb_core/app/model/results/empty.py
openbb_core-1.5.9.dist-info/METADATA
openbb_core-1.5.9.dist-info/WHEEL
openbb_core-1.5.9.dist-info/entry_points.txt
openbb_core-1.5.9.dist-info/RECORD
