Metadata-Version: 2.4
Name: openbb-core
Version: 1.5.9
Summary: OpenBB package with core functionality.
License: AGPL-3.0-only
Author: OpenBB Team
Author-email: hello@openbb.co
Requires-Python: >=3.10,<3.14
Classifier: License :: OSI Approved :: GNU Affero General Public License v3
Classifier: Programming Language :: Python :: 3
Classifier: Programming Language :: Python :: 3.10
Classifier: Programming Language :: Python :: 3.11
Classifier: Programming Language :: Python :: 3.12
Classifier: Programming Language :: Python :: 3.13
Requires-Dist: aiohttp (>=3.13.3)
Requires-Dist: fastapi (>=0.128.0,<0.129.0)
Requires-Dist: html5lib (>=1.1,<2.0)
Requires-Dist: importlib-metadata (>=6.8.0)
Requires-Dist: pandas (>=1.5.3,<3)
Requires-Dist: pydantic (>=2.12.3,<3.0.0)
Requires-Dist: pyjwt (>=2.10.1,<3.0.0)
Requires-Dist: python-dotenv (>=1.0.0,<2.0.0)
Requires-Dist: python-multipart (>=0.0.20,<0.0.21)
Requires-Dist: requests (>=2.32.5,<3.0.0)
Requires-Dist: ruff (>=0.13,<0.14)
Requires-Dist: uuid7 (>=0.1.0,<0.2.0)
Requires-Dist: uvicorn (>=0.40.0,<0.41.0)
Requires-Dist: websockets (>=15.0,<16.0)
